{
  "orgName": "IdP Org",
  "edition": "Developer",
  "features": [
    "Communities",
    "PersonAccounts",
    "IdentityProvisioningFeatures",
    "SalesforceIdentityForCommunities"
  ],
  "hasSampleData": true,
  "settings": {
    "communitiesSettings": {
        "enableNetworksEnabled": true
    },
    "lightningExperienceSettings": {
      "enableS1DesktopEnabled": true
    },
    "chatterSettings": {
      "enableChatter": true
    },
    "userManagementSettings": {
      "enableNewProfileUI": true
    },
    "securitySettings": {
      "enableAdminLoginAsAnyUser": true,
      "sessionSettings": {
        "forceRelogin": false
      }
    },
    "languageSettings": {
      "enableTranslationWorkbench": true
    }
  }
}